cvmplot/__init__.py
cvmplot/cvmplot.py
cvmplot-0.0.3.dist-info/METADATA
cvmplot-0.0.3.dist-info/WHEEL
cvmplot-0.0.3.dist-info/top_level.txt
cvmplot-0.0.3.dist-info/RECORD
