Metadata-Version: 2.1
Name: cvmplot
Version: 0.0.3
Summary: SZQ lab data plot function
Home-page: https://github.com/hbucqp/cvmplot
Author: Qingpo Cui
Author-email: cqp@cau.edu.cn
License: MIT Licence
Keywords: tnseq,dendrogram,phylogram,cgMLST,wgMLST,plot
Platform: any
Classifier: Development Status :: 3 - Alpha
Classifier: Intended Audience :: Developers
Classifier: Topic :: Software Development :: Build Tools
Classifier: License :: OSI Approved :: MIT License
Classifier: Programming Language :: Python :: 3.9
Classifier: Programming Language :: Python :: 3.10
Classifier: Programming Language :: Python :: 3.11
Requires-Dist: Bio
Requires-Dist: pandas (>=2.2.3)
Requires-Dist: setuptools
Requires-Dist: matplotlib (>=3.9.2)
Requires-Dist: numpy (>=1.26.4)
Requires-Dist: scipy (>=1.14.1)
Requires-Dist: tabulate (>=0.9.0)
Requires-Dist: dask (>=2024.9.1)
Requires-Dist: pygenomeviz (>=1.4.1)
